<audio_config version="0.1">
  <server>Jack</server>
  <system_device>Jack Server</system_device>
  <in_busses>
    <bus id="Mic #1">
      <system_ports>
        <port>system:capture_1</port>
      </system_ports>
    </bus>
    <bus id="Mic #2">
      <system_ports>
        <port>system:capture_2</port>
      </system_ports>
    </bus>
  </in_busses>
  <out_busses>
    <bus id="Speaker #1">
      <system_ports>
        <port>system:playback_1</port>
        <port>system:playback_2</port>
      </system_ports>
    </bus>
    <bus id="Speaker #2">
      <system_ports>
        <port>system:playback_3</port>
        <port>system:playback_4</port>
      </system_ports>
    </bus>
  </out_busses>
  <sample_rate>44100</sample_rate>
  <buffer_size>auto</buffer_size>
</audio_config>